{
    "#hash_386890528da51c45": "%hash_63ab8ef48c989062",
    "#hash_317afc5dabc1c012": "#hash_5b60e9678ce1d3a",
    "#hash_1dabe297937704": 1,
    "#hash_359e971d09addafc": "#hash_fc73a1fa4f6cac3b",
    "#hash_6874d9b8fb366f90": "&MP_BR_INGAME/KIOSK_ITEM_SELF_REVIVE",
    "#hash_55a1d7bcf425c844": "lm_heal_stim_syringe_01_blue",
    "#hash_e9bca546ce0eba4e": 4,
    "#hash_cba420031462f836": "brloot_self_revive",
    "#hash_8681642bfa3bff37": "#hash_a4a91670e89a5cc4",
    "#hash_d3eb0030de8df73e": "consumable",
    "#hash_8464122fb6575536": 1,
    "#hash_5ee809f61d319039": "revive",
    "#hash_ed6637ac58196659": "",
    "#hash_95d6d970efccc96d": "common_unrestricted",
    "#hash_7c42466bc0339b10": "#hash_5982dacabfe49a0f",
    "#hash_44f106b00b7b362b": "Loadout",
    "#hash_f5db4eb66109077c": "ui_mp_br_loot_icon_revive_item",
    "#hash_a1c19f0591f01672": "%hash_756561f45de971c4",
    "#hash_b6da4d92ce77e489": "#hash_afeb34a87e316add"
}