{
    "#hash_ce322b78f58639a4": 70,
    "#hash_3a7747bc9807f3c0": [
        {
            "#hash_a76c71da7297bb58": 0,
            "#hash_332e305ca1ca24ca": "#hash_894e891ff2a235b9",
            "#hash_6298e4ace3eb26b3": "#hash_894e891ff2a235b9"
        },
        {
            "#hash_a76c71da7297bb58": 1,
            "#hash_332e305ca1ca24ca": "#stun",
            "#hash_6298e4ace3eb26b3": "#stun"
        },
        {
            "#hash_a76c71da7297bb58": 2,
            "#hash_332e305ca1ca24ca": "#slow",
            "#hash_6298e4ace3eb26b3": "#slow"
        },
        {
            "#hash_a76c71da7297bb58": 3,
            "#hash_332e305ca1ca24ca": "#hash_bac793c46f21a03f",
            "#hash_6298e4ace3eb26b3": "#hash_bac793c46f21a03f"
        }
    ],
    "#hash_332e305ca1ca24ca": "#hash_d6d9226afe570b47",
    "#hash_6298e4ace3eb26b3": "#hash_c42353117753a27f"
}