{
    "#hash_ce322b78f58639a4": "invert_pitch_vehicle_ground_kbm",
    "#hash_87f80f97c9f8bf75": "&OPTIONS/INVERT_VERTICAL_LOOK_GROUND_DESC",
    "#hash_ae4922abee4aa11e": [
        {
            "#hash_d79caab4489a152e": "&OPTIONS/STANDARD"
        },
        {
            "#hash_d79caab4489a152e": "&OPTIONS/INVERTED"
        }
    ],
    "#hash_a20785232d9c4057": "invertPitchVehicleGroundKBM",
    "#hash_58d61dc3eef940dc": "KEYBINDS_GAMEPLAY",
    "#hash_5ee809f61d319039": "Dropdown",
    "#hash_332e305ca1ca24ca": "&OPTIONS/INVERT_VERTICAL_LOOK_GROUND"
}